aliyunsdkpvtz/__init__.py
aliyunsdkpvtz/endpoint.py
aliyunsdkpvtz/request/__init__.py
aliyunsdkpvtz/request/v20180101/AddResolverEndpointRequest.py
aliyunsdkpvtz/request/v20180101/AddResolverRuleRequest.py
aliyunsdkpvtz/request/v20180101/AddUserVpcAuthorizationRequest.py
aliyunsdkpvtz/request/v20180101/AddZoneRecordRequest.py
aliyunsdkpvtz/request/v20180101/AddZoneRequest.py
aliyunsdkpvtz/request/v20180101/BindResolverRuleVpcRequest.py
aliyunsdkpvtz/request/v20180101/BindZoneVpcRequest.py
aliyunsdkpvtz/request/v20180101/CheckZoneNameRequest.py
aliyunsdkpvtz/request/v20180101/DeleteResolverEndpointRequest.py
aliyunsdkpvtz/request/v20180101/DeleteResolverRuleRequest.py
aliyunsdkpvtz/request/v20180101/DeleteUserVpcAuthorizationRequest.py
aliyunsdkpvtz/request/v20180101/DeleteZoneRecordRequest.py
aliyunsdkpvtz/request/v20180101/DeleteZoneRequest.py
aliyunsdkpvtz/request/v20180101/DescribeChangeLogsRequest.py
aliyunsdkpvtz/request/v20180101/DescribeRegionsRequest.py
aliyunsdkpvtz/request/v20180101/DescribeRequestGraphRequest.py
aliyunsdkpvtz/request/v20180101/DescribeResolverAvailableZonesRequest.py
aliyunsdkpvtz/request/v20180101/DescribeResolverEndpointRequest.py
aliyunsdkpvtz/request/v20180101/DescribeResolverEndpointsRequest.py
aliyunsdkpvtz/request/v20180101/DescribeResolverRuleRequest.py
aliyunsdkpvtz/request/v20180101/DescribeResolverRulesRequest.py
aliyunsdkpvtz/request/v20180101/DescribeStatisticSummaryRequest.py
aliyunsdkpvtz/request/v20180101/DescribeSyncEcsHostTaskRequest.py
aliyunsdkpvtz/request/v20180101/DescribeTagsRequest.py
aliyunsdkpvtz/request/v20180101/DescribeUserVpcAuthorizationsRequest.py
aliyunsdkpvtz/request/v20180101/DescribeZoneInfoRequest.py
aliyunsdkpvtz/request/v20180101/DescribeZoneRecordsRequest.py
aliyunsdkpvtz/request/v20180101/DescribeZoneVpcTreeRequest.py
aliyunsdkpvtz/request/v20180101/DescribeZonesRequest.py
aliyunsdkpvtz/request/v20180101/ListTagResourcesRequest.py
aliyunsdkpvtz/request/v20180101/MoveResourceGroupRequest.py
aliyun_python_sdk_pvtz-1.3.0.dist-info/LICENSE
aliyun_python_sdk_pvtz-1.3.0.dist-info/METADATA
aliyun_python_sdk_pvtz-1.3.0.dist-info/WHEEL
aliyun_python_sdk_pvtz-1.3.0.dist-info/top_level.txt
aliyun_python_sdk_pvtz-1.3.0.dist-info/RECORD
